{
  "sources": [
    {
      "name": "CRA Newsroom",
      "category": "Federal Tax & Compliance",
      "url": "https://www.canada.ca/en/news/advanced-news-search/news-results.html?typ=newsreleases&dprtmnt=revenueagency",
      "type": "scrape",
      "source_page": "https://www.canada.ca/en/news/advanced-news-search/news-results.html?typ=newsreleases&dprtmnt=revenueagency"
    },
    {
      "name": "OSFI",
      "category": "Federal Regulator",
      "url": "https://www.osfi-bsif.gc.ca/rss.xml",
      "type": "rss",
      "rss_url": "https://www.osfi-bsif.gc.ca/rss.xml",
      "source_page": "https://www.osfi-bsif.gc.ca/en/news",
      "from_tj": true
    },
    {
      "name": "CAPSA",
      "category": "Pension Industry",
      "url": "https://www.capsa-acor.org/news",
      "type": "scrape",
      "source_page": "https://www.capsa-acor.org/news"
    },
    {
      "name": "Canadian Institute of Actuaries",
      "category": "Pension Industry",
      "url": "https://www.cia-ica.ca/news/",
      "type": "scrape",
      "source_page": "https://www.cia-ica.ca/news/"
    },
    {
      "name": "ACPM (Association of Canadian Pension Management)",
      "category": "Pension Industry",
      "url": "https://www.acpm.com/news",
      "type": "scrape",
      "source_page": "https://www.acpm.com/news"
    },
    {
      "name": "FSRAO Ontario",
      "category": "Pension Industry",
      "url": "https://www.fsrao.ca/announcements?keywords=&news_type=All&news_sectors=726&news_audience=All",
      "type": "scrape",
      "source_page": "https://www.fsrao.ca/announcements?keywords=&news_type=All&news_sectors=726&news_audience=All",
      "from_tj": true
    },
    {
      "name": "BCFSA (BC Financial Services Authority)",
      "category": "Pension Industry",
      "url": "https://www.bcfsa.ca/about-us/news?search=&page=0&f%5B0%5D=industry%3Apensions",
      "type": "scrape",
      "source_page": "https://www.bcfsa.ca/about-us/news?search=&page=0&f%5B0%5D=industry%3Apensions",
      "notes": "JavaScript-rendered with pension industry filter, requires Selenium WebDriver.",
      "from_tj": true
    },
    {
      "name": "Retraite Quebec",
      "category": "Pension Industry",
      "url": "https://www.retraitequebec.gouv.qc.ca/fr/actualites/Pages/actualites.aspx",
      "type": "scrape",
      "source_page": "https://www.retraitequebec.gouv.qc.ca/fr/actualites/Pages/actualites.aspx",
      "from_tj": true
    },
    {
      "name": "FCAA Saskatchewan",
      "category": "Pension Industry",
      "url": "https://fcaa.gov.sk.ca/whats-new/news",
      "type": "scrape",
      "source_page": "https://fcaa.gov.sk.ca/whats-new/news"
    },
    {
      "name": "FCNB New Brunswick",
      "category": "Pension Industry",
      "url": "https://fcnb.ca/en/news-alerts",
      "type": "scrape",
      "source_page": "https://fcnb.ca/en/news-alerts",
      "from_tj": true
    },
    {
      "name": "Government of Manitoba Pensions",
      "category": "Pension Industry",
      "url": "https://www.gov.mb.ca/pension",
      "type": "scrape",
      "source_page": "https://www.gov.mb.ca/pension"
    },
    {
      "name": "Government of NL Pensions",
      "category": "Pension Industry",
      "url": "https://www.gov.nl.ca/gs/",
      "type": "scrape",
      "source_page": "https://www.gov.nl.ca/gs/",
      "from_tj": true
    },
    {
      "name": "Alberta Pensions",
      "category": "Pension Industry",
      "url": "https://www.alberta.ca/pensions-legislation-updates",
      "type": "scrape",
      "source_page": "https://www.alberta.ca/pensions-legislation-updates",
      "from_tj": true
    },
    {
      "name": "The Royal Gazette (Bermuda)",
      "category": "Caribbean News",
      "url": "https://www.royalgazette.com/politics/news/",
      "type": "scrape",
      "source_page": "https://www.royalgazette.com/politics/news/",
      "from_tj": true,
      "keywords": ["pension", "retirement", "contribution", "civil service", "benefits"],
      "location": "Bermuda"
    },
    {
      "name": "Nassau Guardian (Bahamas)",
      "category": "Caribbean News",
      "url": "https://www.thenassauguardian.com/news/",
      "type": "scrape",
      "source_page": "https://www.thenassauguardian.com/news/",
      "from_tj": true,
      "keywords": ["pension", "national insurance", "benefits", "NHI"],
      "location": "Bahamas"
    },
    {
      "name": "Trinidad Guardian",
      "category": "Caribbean News",
      "url": "https://www.guardian.co.tt/business",
      "type": "scrape",
      "source_page": "https://www.guardian.co.tt/business",
      "from_tj": true,
      "keywords": ["NIS", "pension", "actuarial", "retirement"],
      "location": "Trinidad & Tobago"
    },
    {
      "name": "Trinidad & Tobago Newsday",
      "category": "Caribbean News",
      "url": "https://newsday.co.tt/category/business/",
      "type": "scrape",
      "source_page": "https://newsday.co.tt/category/business/",
      "from_tj": true,
      "keywords": ["health sector", "insurance", "pension fund"],
      "location": "Trinidad & Tobago"
    },
    {
      "name": "Jamaica Gleaner",
      "category": "Caribbean News",
      "url": "https://jamaica-gleaner.com/business",
      "type": "scrape",
      "source_page": "https://jamaica-gleaner.com/business",
      "from_tj": true,
      "keywords": ["insurance", "pension", "financial", "JN financial"],
      "location": "Jamaica"
    },
    {
      "name": "Jamaica Observer",
      "category": "Caribbean News",
      "url": "https://www.jamaicaobserver.com/business/",
      "type": "scrape",
      "source_page": "https://www.jamaicaobserver.com/business/",
      "from_tj": true,
      "keywords": ["pension", "financial", "insurance", "benefits"],
      "location": "Jamaica"
    },
    {
      "name": "Other News Sources",
      "category": "Other News Sources",
      "url": "https://news.google.com/search?q=pension%20canada%20regulation&hl=en-CA&gl=CA&ceid=CA%3Aen",
      "type": "scrape",
      "source_page": "https://news.google.com/search?q=pension%20canada%20regulation&hl=en-CA&gl=CA&ceid=CA%3Aen"
    }
  ],
  "notes": "Verified sources mapped to user-specified categories: Federal Tax & Compliance, Federal Regulator, Pension Industry, Caribbean News, Other News Sources."
}
